semantic_split/SentenceSimilarity.py
semantic_split/__init__.py
semantic_split/splitters/SimilarSentenceSplitter.py
semantic_split/splitters/SpacySentenceSplitter.py
semantic_split/splitters/Splitter.py
semantic_split-0.1.0.dist-info/METADATA
semantic_split-0.1.0.dist-info/WHEEL
semantic_split-0.1.0.dist-info/RECORD
