Metadata-Version: 2.1
Name: semantic-split
Version: 0.1.0
Summary: A better way to split (chunk/group) your text before inserting them into an LLM/Vector DB.
License: MIT
Author: Agam More
Author-email: agam@agam.me
Classifier: License :: OSI Approved :: MIT License
Classifier: Programming Language :: Python :: 2
Classifier: Programming Language :: Python :: 2.7
Classifier: Programming Language :: Python :: 3
Classifier: Programming Language :: Python :: 3.4
Classifier: Programming Language :: Python :: 3.5
Classifier: Programming Language :: Python :: 3.6
Classifier: Programming Language :: Python :: 3.7
Classifier: Programming Language :: Python :: 3.8
Classifier: Programming Language :: Python :: 3.9
Classifier: Programming Language :: Python :: 3.10
Classifier: Programming Language :: Python :: 3.11
Requires-Dist: sentence-transformers (>=2.2.2,<3.0.0)
Requires-Dist: spacy (>=3.5.3,<4.0.0)
